seedboxsync_front/__init__.py
seedboxsync_front/app.py
seedboxsync_front/db.py
seedboxsync_front/controlers/api.py
seedboxsync_front/controlers/homepage.py
seedboxsync_front/controlers/page_not_found.py
seedboxsync_front/static/favicon.png
seedboxsync_front/static/logo.png
seedboxsync_front/static/dist/fa-brands-400.woff2
seedboxsync_front/static/dist/fa-regular-400.woff2
seedboxsync_front/static/dist/fa-solid-900.woff2
seedboxsync_front/static/dist/main.css
seedboxsync_front/static/dist/main.js
seedboxsync_front/static/src/main.js
seedboxsync_front/static/src/js/bulma_notification.js
seedboxsync_front/static/src/scss/bulma.scss
seedboxsync_front/static/src/scss/main.scss
seedboxsync_front/templates/404.html
seedboxsync_front/templates/base.html
seedboxsync_front/templates/homepage.html
seedboxsync_front/templates/components/footer.html
seedboxsync_front/templates/components/javascripts.html
seedboxsync_front/templates/components/messages.html
seedboxsync_front/templates/components/navbar.html
seedboxsync_front-2.0.1a1.dist-info/entry_points.txt
seedboxsync_front-2.0.1a1.dist-info/licenses/LICENSE
seedboxsync_front-2.0.1a1.dist-info/WHEEL
seedboxsync_front-2.0.1a1.dist-info/METADATA
seedboxsync_front-2.0.1a1.dist-info/RECORD
