Metadata-Version: 2.4
Name: seedboxsync-front
Version: 2.0.1a1
Summary: The frontend for SeedboxSync.
Author-email: Guillaume Kulakowski <guillaume@kulakowski.fr>
Requires-Python: >=3.10
License-Expression: GPL-2.0-only
License-File: LICENSE
Requires-Dist: flask
Requires-Dist: pyyaml
Requires-Dist: peewee
Requires-Dist: seedboxsync>=3.2.0
Requires-Dist: flake8 ; extra == "dev"
Requires-Dist: pytest ; extra == "dev"
Requires-Dist: pytest-cov ; extra == "dev"
Requires-Dist: flit ; extra == "dev"
Project-URL: Home, https://llaumgui.github.io/seedboxsync/
Project-URL: Source, https://github.com/llaumgui/seedboxsync-front
Provides-Extra: dev
